


{
 "resultCount":1,
 "results": [
{
"ipadScreenshotUrls":["http://a5.mzstatic.com/us/r30/Purple7/v4/01/ae/39/01ae3953-0720-86ca-6c7c-bc0472349153/screen480x480.jpeg", "http://a2.mzstatic.com/us/r30/Purple1/v4/ce/15/60/ce15600b-242b-3d32-0ef4-26c11b16506c/screen480x480.jpeg", "http://a5.mzstatic.com/us/r30/Purple7/v4/39/56/87/39568764-6624-4b9d-428d-28d2c2fac483/screen480x480.jpeg", "http://a5.mzstatic.com/us/r30/Purple7/v4/f6/76/bd/f676bd5b-1a55-43b3-f8ce-c4e09d3d14b0/screen480x480.jpeg", "http://a1.mzstatic.com/us/r30/Purple1/v4/3a/ff/c0/3affc07a-c95f-d32f-bdd0-ff031c14be67/screen480x480.jpeg"], "appletvScreenshotUrls":[], "artworkUrl512":"http://is5.mzstatic.com/image/thumb/Purple69/v4/ef/14/8e/ef148e61-e9b1-a1fa-0af5-a20eb9579d02/source/512x512bb.jpg", "artistViewUrl":"https://itunes.apple.com/us/developer/alexander-ivanov/id734258593?uo=4", "artworkUrl60":"http://is5.mzstatic.com/image/thumb/Purple69/v4/ef/14/8e/ef148e61-e9b1-a1fa-0af5-a20eb9579d02/source/60x60bb.jpg", "artworkUrl100":"http://is5.mzstatic.com/image/thumb/Purple69/v4/ef/14/8e/ef148e61-e9b1-a1fa-0af5-a20eb9579d02/source/100x100bb.jpg", "kind":"software", "features":["iosUniversal"], 
"supportedDevices":["iPhone4-iPhone4", "iPad2Wifi-iPad2Wifi", "iPad23G-iPad23G", "iPhone4S-iPhone4S", "iPadThirdGen-iPadThirdGen", "iPadThirdGen4G-iPadThirdGen4G", "iPhone5-iPhone5", "iPodTouchFifthGen-iPodTouchFifthGen", "iPadFourthGen-iPadFourthGen", "iPadFourthGen4G-iPadFourthGen4G", "iPadMini-iPadMini", "iPadMini4G-iPadMini4G", "iPhone5c-iPhone5c", "iPhone5s-iPhone5s", "iPadAir-iPadAir", "iPadAirCellular-iPadAirCellular", "iPadMiniRetina-iPadMiniRetina", "iPadMiniRetinaCellular-iPadMiniRetinaCellular", "iPhone6-iPhone6", "iPhone6Plus-iPhone6Plus", "iPadAir2-iPadAir2", "iPadAir2Cellular-iPadAir2Cellular", "iPadMini3-iPadMini3", "iPadMini3Cellular-iPadMini3Cellular", "iPodTouchSixthGen-iPodTouchSixthGen", "iPhone6s-iPhone6s", "iPhone6sPlus-iPhone6sPlus", "iPadMini4-iPadMini4", "iPadMini4Cellular-iPadMini4Cellular", "iPadPro-iPadPro", "iPadProCellular-iPadProCellular", "iPadPro97-iPadPro97", "iPadPro97Cellular-iPadPro97Cellular", "iPhoneSE-iPhoneSE", "iPhone7-iPhone7", "iPhone7Plus-iPhone7Plus", "iPad611-iPad611", "iPad612-iPad612"], 
"screenshotUrls":["http://a1.mzstatic.com/us/r30/Purple7/v4/a7/45/62/a745626d-df29-b4e9-559e-4c6a5df81b02/screen696x696.jpeg", "http://a2.mzstatic.com/us/r30/Purple7/v4/84/d3/62/84d36226-0956-3770-8754-6fcc26ff28e2/screen696x696.jpeg", "http://a5.mzstatic.com/us/r30/Purple7/v4/b5/05/fb/b505fbde-5c34-1e6b-26f9-c01d6709d6ae/screen696x696.jpeg", "http://a3.mzstatic.com/us/r30/Purple7/v4/c0/b9/cf/c0b9cfdb-b168-ef38-21ec-678c715ba9be/screen696x696.jpeg", "http://a4.mzstatic.com/us/r30/Purple5/v4/a8/d6/ee/a8d6ee58-7f5a-49bc-80d5-e2734a9209f0/screen696x696.jpeg"], "advisories":[], "isGameCenterEnabled":false, "averageUserRatingForCurrentVersion":1.0, "languageCodesISO2A":["AR", "DA", "NL", "EN", "FI", "FR", "DE", "EL", "ID", "IT", "JA", "KO", "MS", "NB", "PT", "RU", "ZH", "ES", "SV", "TH", "ZH", "TR", "VI"], "fileSizeBytes":"7990272", "sellerUrl":"https://www.facebook.com/airtasks", "userRatingCountForCurrentVersion":2, "trackContentRating":"4+", "trackCensoredName":"Air Tasks - To-Do List with Reminders", "trackViewUrl":"https://itunes.apple.com/us/app/air-tasks-to-do-list-with-reminders/id734258590?mt=8&uo=4", "contentAdvisoryRating":"4+", "genreIds":["6007", "6000"], "formattedPrice":"Free", "minimumOsVersion":"7.0", "currentVersionReleaseDate":"2016-02-23T21:27:36Z", "currency":"USD", "wrapperType":"software", "version":"3.14.5", "artistId":734258593, "artistName":"Alexander Ivanov", "genres":["Productivity", "Business"], "price":0.00, 
"description":"Air Tasks is an extremely minimalistic TO-DO list. It was designed this way to help you focus on what is really important - doing. Yet it supports latest technologies and allows to exchange TO-DOs with other people. This simple and functional app will become the best companion in the journey to increase your productivity. Install Air Tasks today and see for yourself.\n\n«Air Tasks is a free gesture-based app for the iPad or iPhone that's perfect for those of you who take a minimalist approach to your to-do list.» - Engadget\n\nUSER REVIEWS\n\n«I have used this app many time and have been very pleased. Easy to use and very user friendly.» - uguroney\n\n«Excellent tool! I use it constantly. It's beautiful to look at and effective.» - AA\\15\n\nFEATURES\n\n• Notification center widget.\n• Interactive notifications.\n• Gesture-based interface.\n• Sending and receiving reminders.\n• Productivity statistics.\n• iCloud support.\n• Continuous task reminders.\n• Productivity improvement advices.\n• Serial addition.\n• Sounds and reminders customization.\n• Repeating tasks according to schedule.\n• Subtasks addition.\n• History of completed tasks.\n• Universal app for iPhone and iPad.\n\nYou can install Air Tasks for free right now and discover all of its features for yourself or you can continue reading this long and boring description.\n\nCOLLECT\n\nJust write down everything to Air Tasks, keep your mind free from clutter.\n\nEasily collect all of your tasks in one place: \n• pull down and release the list to add new task (keep pulling down until you see ∞ instead of + to enter serial addition mode), \n• touch task's title to change it. \n\nPROCESS\n\nDo not pile up collected tasks, complete those which take less than 2 minutes, defer, calendar or delegate others. \n\nBy swiping the task to the right you can: \n• defer it for a day, week, month, year, or undefined period, \n• calendar it for the specific date and set a reminder, \n• delegate it to a person from your contact list. \nTouch the image to the left of the task's title to change time, date, or person. \n\nORGANIZE\n\nAir Tasks organizes your tasks, but you can flexibly manage them after. \n\nTame your task list by finding every task its place: \n• change order of tasks with the same time, date, or person by touching and holding a task and then moving it to the new place, \n• delete obsolete tasks by swiping them to the left. \n\nREVIEW\n\nPeriodically revise your schedule, Air Tasks already organized it for you in a convenient way. \n\nAll collected tasks are at the top of the list. Try to get them to 0 by processing them when you have a free minute. \nThey are followed by ordered list of processed tasks, beginning with overdue and ending with ones that are in far future. Always be aware of your today's schedule. \nAfter them you will find delegated tasks. Monitor their execution by the assigned person. \nDone tasks are at the end of the list. You will be surprised by their quantity after some time of Air Tasks usage. \n\nDO\n\nEnjoy your work and let Air Tasks manage the rest.\n\nBe productive: \n• mark task as done by swiping them to the right,\n• clear the list from completed tasks by pulling it up and then releasing.", "bundleId":"com.alexivanov.done", "trackId":734258590, "trackName":"Air Tasks - To-Do List with Reminders", "isVppDeviceBasedLicensingEnabled":true, "primaryGenreName":"Productivity", "releaseDate":"2013-12-03T06:05:57Z", "releaseNotes":"Bug fixes and performance improvements.", "primaryGenreId":6007, "sellerName":"Alexander Ivanov", "averageUserRating":4.0, "userRatingCount":47}]
}


